hatch_demo_2403141030/__about__.py
hatch_demo_2403141030/__init__.py
hatch_demo_2403141030-0.2.0.dist-info/METADATA
hatch_demo_2403141030-0.2.0.dist-info/WHEEL
hatch_demo_2403141030-0.2.0.dist-info/licenses/LICENSE.txt
hatch_demo_2403141030-0.2.0.dist-info/RECORD
